createWeb/setDjango.py
setupDjango-0.0.2.dist-info/LICENSE
setupDjango-0.0.2.dist-info/METADATA
setupDjango-0.0.2.dist-info/WHEEL
setupDjango-0.0.2.dist-info/top_level.txt
setupDjango-0.0.2.dist-info/RECORD
